petsafe/__init__.py
petsafe/__main__.py
petsafe/client.py
petsafe/const.py
petsafe/devices.py
petsafe-2.0.7.dist-info/LICENSE
petsafe-2.0.7.dist-info/METADATA
petsafe-2.0.7.dist-info/WHEEL
petsafe-2.0.7.dist-info/top_level.txt
petsafe-2.0.7.dist-info/RECORD
