Metadata-Version: 2.1
Name: petsafe
Version: 2.0.7
Summary: Provides ability to connect and control a PetSafe Smart Feed and Scoopfree device using the PetSafe API.
Home-page: https://github.com/dcmeglio/petsafe
Author: Jordan Stremming & Dominick Meglio
Author-email: dmeglio@gmail.com
License: MIT
Classifier: Programming Language :: Python :: 3
Classifier: License :: OSI Approved :: MIT License
Classifier: Operating System :: OS Independent
Requires-Python: >=3.6
License-File: LICENSE
Requires-Dist: httpx
Requires-Dist: botocore
